holidayapi/__init__.py
python_holidayapi-1.1.0.dist-info/LICENSE
python_holidayapi-1.1.0.dist-info/METADATA
python_holidayapi-1.1.0.dist-info/WHEEL
python_holidayapi-1.1.0.dist-info/top_level.txt
python_holidayapi-1.1.0.dist-info/RECORD
