Metadata-Version: 1.0
Name: python-holidayapi
Version: 1.1.0
Summary: Official Python library for Holiday API
Home-page: https://holidayapi.com
Author: Josh Sherman
Author-email: hello@holidayapi.com
License: MIT
Keywords: python,holidayapi,holiday,api
Platform: UNKNOWN
